aioriak/__init__.py
aioriak/bucket.py
aioriak/client.py
aioriak/content.py
aioriak/error.py
aioriak/mapreduce.py
aioriak/resolver.py
aioriak/riak_object.py
aioriak/transport.py
aioriak/datatypes/__init__.py
aioriak/datatypes/counter.py
aioriak/datatypes/datatype.py
aioriak/datatypes/flag.py
aioriak/datatypes/map.py
aioriak/datatypes/register.py
aioriak/datatypes/set.py
aioriak/datatypes/types.py
aioriak-0.2.0.dist-info/LICENSE.txt
aioriak-0.2.0.dist-info/METADATA
aioriak-0.2.0.dist-info/WHEEL
aioriak-0.2.0.dist-info/top_level.txt
aioriak-0.2.0.dist-info/RECORD
