Metadata-Version: 2.1
Name: aioriak
Version: 0.2.0
Summary: Async implementation of Riak DB python client
Home-page: https://github.com/rambler-digital-solutions/aioriak
Author: Makc Belousov
Author-email: m.belousov@rambler-co.ru
License: MIT
Keywords: riak asyncio client
Platform: UNKNOWN
Classifier: Development Status :: 3 - Alpha
Classifier: Intended Audience :: Developers
Classifier: License :: OSI Approved :: MIT License
Classifier: Programming Language :: Python :: 3.6
Classifier: Programming Language :: Python :: 3.5
Classifier: Programming Language :: Python :: 3 :: Only
Classifier: Topic :: Database
Classifier: Topic :: Software Development :: Libraries :: Python Modules
Requires-Dist: riak (==2.7.0)
Provides-Extra: dev
Requires-Dist: Sphinx (==2.0.1) ; extra == 'dev'
Requires-Dist: sphinx-autobuild (==0.7.1) ; extra == 'dev'
Requires-Dist: sphinx-rtd-theme (==0.4.3) ; extra == 'dev'
Requires-Dist: sphinxcontrib-asyncio (==0.2.0) ; extra == 'dev'
